basty/behavior_mapping/behavioral_states.py
basty/behavior_mapping/behavioral_windows.py
basty/experiment_processing/experiment_info.py
basty/experiment_processing/experiment_outlining.py
basty/feature_extraction/body_pose.py
basty/feature_extraction/spatiotemporal_features.py
basty/feature_extraction/wavelet_transformation.py
basty/project/behavior_mapping.py
basty/project/experiment_processing.py
basty/project/feature_extraction.py
basty/project/helper.py
basty/utils/annotations.py
basty/utils/evaluation.py
basty/utils/io.py
basty/utils/misc.py
basty/utils/postprocessing.py
basty/utils/preprocessing.py
basty-0.1.1.dist-info/WHEEL
basty-0.1.1.dist-info/METADATA
basty-0.1.1.dist-info/RECORD
